Metadata-Version: 1.0
Name: GausBinom-probability-Dist
Version: 0.1
Summary: Gaussian and Bionomial distributions
Home-page: UNKNOWN
Author: Rojan Saghian
Author-email: UNKNOWN
License: UNKNOWN
Platform: UNKNOWN
